epanns/__init__.py
epanns/__main__.py
epanns/cli.py
epanns/config/audioset_labels.csv
epanns/config/domestic_labels.csv
epanns/lib/inference.py
epanns/lib/models.py
epanns/lib/utils.py
epanns/predict.py
epanns-0.1.5.dist-info/LICENSE
epanns-0.1.5.dist-info/METADATA
epanns-0.1.5.dist-info/WHEEL
epanns-0.1.5.dist-info/entry_points.txt
epanns-0.1.5.dist-info/RECORD
