Metadata-Version: 2.3
Name: epanns
Version: 0.1.5
Summary: Categorise sounds within an audio file
License: MIT
Author: Chris Baume
Author-email: chris@bau.me
Requires-Python: >= 3.9
Classifier: License :: OSI Approved :: MIT License
Classifier: Programming Language :: Python :: 3
Classifier: Programming Language :: Python :: 3.9
Classifier: Programming Language :: Python :: 3.10
Classifier: Programming Language :: Python :: 3.11
Classifier: Programming Language :: Python :: 3.12
Classifier: Programming Language :: Python :: 3.13
Requires-Dist: librosa (>=0.8)
Requires-Dist: matplotlib
Requires-Dist: numpy (<2)
Requires-Dist: platformdirs
Requires-Dist: requests
Requires-Dist: torch (<2)
Requires-Dist: torchlibrosa
Requires-Dist: typer
